{"version": "https://jsonfeed.org/version/1", "title": "GND 70yrs expired list", "home_page_url": "https://lobid.org", "feed_url": "https://raw.githubusercontent.com/MichaelMarkert/rss/refs/heads/main/gnd_70yrsexp.json", "items": [{"id": "https://d-nb.info/gnd/1037881621", "image": "", "title": "Voigtl\u00e4nder, Friedrich", "content_text": "Fotograf | 1955-05-13", "url": "https://d-nb.info/gnd/1037881621", "date_published": "2025-05-13T05:23:41.361636"}, {"id": "https://d-nb.info/gnd/1100091637", "image": "", "title": "Palkoska, Emil", "content_text": " | 1955-05-13", "url": "https://d-nb.info/gnd/1100091637", "date_published": "2025-05-13T05:23:41.361636"}, {"id": "https://d-nb.info/gnd/1055314946", "image": "", "title": "Foerster, Ernst", "content_text": "Schiffbauer, Ingenieur | 1955-05-13", "url": "https://d-nb.info/gnd/1055314946", "date_published": "2025-05-13T05:23:41.361636"}, {"id": "https://d-nb.info/gnd/138088446", "image": "", "title": "Gr\u00e4bke, Hans Arnold", "content_text": "Museumsdirektor, Kunsthistoriker | 1955-05-13", "url": "https://d-nb.info/gnd/138088446", "date_published": "2025-05-13T05:23:41.361636"}, {"id": "https://d-nb.info/gnd/1088335659", "image": "", "title": "Irmler, Erich", "content_text": "P\u00e4dagoge | 1955-05-13", "url": "https://d-nb.info/gnd/1088335659", "date_published": "2025-05-13T05:23:41.361636"}, {"id": "https://d-nb.info/gnd/1302201506", "image": "", "title": "Wieland-Burckhardt, Valerie", "content_text": "Malerin | 1955-05-13", "url": "https://d-nb.info/gnd/1302201506", "date_published": "2025-05-13T05:23:41.361636"}]}