{"version": "https://jsonfeed.org/version/1", "title": "Wikidata 70yrs expired list", "home_page_url": "https://wikidata.org", "feed_url": "https://raw.githubusercontent.com/MichaelMarkert/rss/refs/heads/main/mb_jobs.json", "items": [{"id": "http://www.wikidata.org/entity/Q16369428", "image": "", "title": "Q16369428", "content_text": "writer, public figure, opinion journalist, philologist | 1955-09-25", "url": "http://www.wikidata.org/entity/Q16369428", "date_published": "2025-09-25T09:25:06.178973"}, {"id": "http://www.wikidata.org/entity/Q94944934", "image": "", "title": "Adolf Pr\u00fcmers", "content_text": "composer, choir director, organist | 1955-09-25", "url": "http://www.wikidata.org/entity/Q94944934", "date_published": "2025-09-25T09:25:06.178973"}, {"id": "http://www.wikidata.org/entity/Q65851710", "image": "", "title": "Adriaan Synco Oppenheim", "content_text": "university teacher, legal counselor | 1955-09-25", "url": "http://www.wikidata.org/entity/Q65851710", "date_published": "2025-09-25T09:25:06.178973"}, {"id": "http://www.wikidata.org/entity/Q98346641", "image": "", "title": "Ana\u00efs Ronc-D\u00e9saymonet", "content_text": "writer, teacher | 1955-09-25", "url": "http://www.wikidata.org/entity/Q98346641", "date_published": "2025-09-25T09:25:06.178973"}, {"id": "http://www.wikidata.org/entity/Q710678", "image": "", "title": "Arthur Millspaugh", "content_text": "political scientist | 1955-09-25", "url": "http://www.wikidata.org/entity/Q710678", "date_published": "2025-09-25T09:25:06.178973"}, {"id": "http://www.wikidata.org/entity/Q2115403", "image": "", "title": "Charles Daniel White", "content_text": "Catholic priest, Catholic bishop | 1955-09-25", "url": "http://www.wikidata.org/entity/Q2115403", "date_published": "2025-09-25T09:25:06.178973"}, {"id": "http://www.wikidata.org/entity/Q1288982", "image": "", "title": "Eduard Kehlmann", "content_text": "writer | 1955-09-25", "url": "http://www.wikidata.org/entity/Q1288982", "date_published": "2025-09-25T09:25:06.178973"}, {"id": "http://www.wikidata.org/entity/Q75919", "image": "", "title": "Franz Rellich", "content_text": "mathematician, university teacher | 1955-09-25", "url": "http://www.wikidata.org/entity/Q75919", "date_published": "2025-09-25T09:25:06.178973"}, {"id": "http://www.wikidata.org/entity/Q3770416", "image": "", "title": "Giuseppe De Falco", "content_text": "politician | 1955-09-25", "url": "http://www.wikidata.org/entity/Q3770416", "date_published": "2025-09-25T09:25:06.178973"}, {"id": "http://www.wikidata.org/entity/Q17351458", "image": "", "title": "Hendrik Josephus Pos", "content_text": "writer, scientist, professor, university teacher, philologist, philosopher, linguist, classical philologist | 1955-09-25", "url": "http://www.wikidata.org/entity/Q17351458", "date_published": "2025-09-25T09:25:06.178973"}, {"id": "http://www.wikidata.org/entity/Q60242522", "image": "", "title": "Johannes Coppenrath", "content_text": "photographer | 1955-09-25", "url": "http://www.wikidata.org/entity/Q60242522", "date_published": "2025-09-25T09:25:06.178973"}, {"id": "http://www.wikidata.org/entity/Q14575434", "image": "", "title": "John R. Perry", "content_text": "military officer | 1955-09-25", "url": "http://www.wikidata.org/entity/Q14575434", "date_published": "2025-09-25T09:25:06.178973"}, {"id": "http://www.wikidata.org/entity/Q1709557", "image": "", "title": "Jos\u00e9 Pascual Tamborini", "content_text": "physician, politician | 1955-09-25", "url": "http://www.wikidata.org/entity/Q1709557", "date_published": "2025-09-25T09:25:06.178973"}, {"id": "http://www.wikidata.org/entity/Q6687045", "image": "", "title": "Louis Drucke", "content_text": "baseball player | 1955-09-25", "url": "http://www.wikidata.org/entity/Q6687045", "date_published": "2025-09-25T09:25:06.178973"}, {"id": "http://www.wikidata.org/entity/Q257114", "image": "", "title": "Martha Norelius", "content_text": "swimmer | 1955-09-25", "url": "http://www.wikidata.org/entity/Q257114", "date_published": "2025-09-25T09:25:06.178973"}, {"id": "http://www.wikidata.org/entity/Q52063685", "image": "", "title": "Max Wieczorek", "content_text": "painter | 1955-09-25", "url": "http://www.wikidata.org/entity/Q52063685", "date_published": "2025-09-25T09:25:06.178973"}, {"id": "http://www.wikidata.org/entity/Q24939367", "image": "", "title": "Rakhmabai", "content_text": "physician | 1955-09-25", "url": "http://www.wikidata.org/entity/Q24939367", "date_published": "2025-09-25T09:25:06.178973"}, {"id": "http://www.wikidata.org/entity/Q111152181", "image": "", "title": "Raymond Joseph Kresensky", "content_text": " | 1955-09-25", "url": "http://www.wikidata.org/entity/Q111152181", "date_published": "2025-09-25T09:25:06.178973"}, {"id": "http://www.wikidata.org/entity/Q4561871", "image": "", "title": "Shigeo \u014cdachi", "content_text": "politician | 1955-09-25", "url": "http://www.wikidata.org/entity/Q4561871", "date_published": "2025-09-25T09:25:06.178973"}, {"id": "http://www.wikidata.org/entity/Q11450000", "image": "", "title": "Sh\u014dtar\u014d Moriyasu", "content_text": "pianist | 1955-09-25", "url": "http://www.wikidata.org/entity/Q11450000", "date_published": "2025-09-25T09:25:06.178973"}, {"id": "http://www.wikidata.org/entity/Q3588493", "image": "", "title": "\u00c9mile Fabre", "content_text": "playwright, theatrical director | 1955-09-25", "url": "http://www.wikidata.org/entity/Q3588493", "date_published": "2025-09-25T09:25:06.178973"}, {"id": "http://www.wikidata.org/entity/Q76065121", "image": "", "title": "Brenda Katharine MacLeod", "content_text": " | 1955-09-25", "url": "http://www.wikidata.org/entity/Q76065121", "date_published": "2025-09-25T09:25:06.178973"}, {"id": "http://www.wikidata.org/entity/Q23613336", "image": "", "title": "Charles Hammond", "content_text": "cricketer | 1955-09-25", "url": "http://www.wikidata.org/entity/Q23613336", "date_published": "2025-09-25T09:25:06.178973"}, {"id": "http://www.wikidata.org/entity/Q11585870", "image": "", "title": "Hideaki Ishikawa", "content_text": "civil engineer | 1955-09-25", "url": "http://www.wikidata.org/entity/Q11585870", "date_published": "2025-09-25T09:25:06.178973"}, {"id": "http://www.wikidata.org/entity/Q89590177", "image": "", "title": "Kenneth Bowman", "content_text": "lepidopterist, collector | 1955-09-25", "url": "http://www.wikidata.org/entity/Q89590177", "date_published": "2025-09-25T09:25:06.178973"}, {"id": "http://www.wikidata.org/entity/Q75643520", "image": "", "title": "Lowry Arthur Casamaijor Cole", "content_text": " | 1955-09-25", "url": "http://www.wikidata.org/entity/Q75643520", "date_published": "2025-09-25T09:25:06.178973"}]}